<?xml version="1.0" encoding="UTF-8"?><config>
<step nr="1">
<cases>
<de.mhus.cherry.reactive.examples.simple1.S1Pool canonical="de.mhus.cherry.reactive.examples.simple1.S1Pool" name="S1Pool" scheduled="0" state="RUNNING" uri="bpm://de.mhus.cherry.reactive.examples.simple1.S1Process:0.0.1/de.mhus.cherry.reactive.examples.simple1.S1Pool">
<parameters text1="trigger" text2=""/>
</de.mhus.cherry.reactive.examples.simple1.S1Pool>
</cases>
<nodes>
<de.mhus.cherry.reactive.examples.simple1.S1Start1 assigned="null" canonical="de.mhus.cherry.reactive.examples.simple1.S1Start1" name="S1Start1" state="RUNNING" suspended="RUNNING" tryCount="3" type="NODE">
<parameters/>
</de.mhus.cherry.reactive.examples.simple1.S1Start1>
<de.mhus.cherry.reactive.model.engine.RuntimeNode assigned="null" canonical="de.mhus.cherry.reactive.model.engine.RuntimeNode" name="runtime" state="WAITING" suspended="WAITING" tryCount="0" type="RUNTIME">
<parameters msg.0="flow:540ec11c-74a7-4895-8290-7e9a6e5383c4,S1Start1 doNodeLifecycle init:true" msg.1="flow:540ec11c-74a7-4895-8290-7e9a6e5383c4,S1Start1 doActivityStop"/>
</de.mhus.cherry.reactive.model.engine.RuntimeNode>
</nodes>
</step>
<step nr="2">
<cases>
<de.mhus.cherry.reactive.examples.simple1.S1Pool canonical="de.mhus.cherry.reactive.examples.simple1.S1Pool" name="S1Pool" scheduled="0" state="RUNNING" uri="bpm://de.mhus.cherry.reactive.examples.simple1.S1Process:0.0.1/de.mhus.cherry.reactive.examples.simple1.S1Pool">
<parameters text1="trigger" text2=""/>
</de.mhus.cherry.reactive.examples.simple1.S1Pool>
</cases>
<nodes>
<de.mhus.cherry.reactive.examples.simple1.S1Start1 assigned="null" canonical="de.mhus.cherry.reactive.examples.simple1.S1Start1" name="S1Start1" state="CLOSED" suspended="CLOSED" tryCount="3" type="NODE">
<parameters/>
</de.mhus.cherry.reactive.examples.simple1.S1Start1>
<de.mhus.cherry.reactive.examples.simple1.S1StepMain assigned="null" canonical="de.mhus.cherry.reactive.examples.simple1.S1StepMain" name="S1StepMain" state="RUNNING" suspended="RUNNING" tryCount="3" type="NODE">
<parameters/>
</de.mhus.cherry.reactive.examples.simple1.S1StepMain>
<de.mhus.cherry.reactive.model.engine.RuntimeNode assigned="null" canonical="de.mhus.cherry.reactive.model.engine.RuntimeNode" name="runtime" state="WAITING" suspended="WAITING" tryCount="0" type="RUNTIME">
<parameters msg.0="flow:540ec11c-74a7-4895-8290-7e9a6e5383c4,S1Start1 doNodeLifecycle init:true" msg.1="flow:540ec11c-74a7-4895-8290-7e9a6e5383c4,S1Start1 doActivityStop" msg.2="flow:540ec11c-74a7-4895-8290-7e9a6e5383c4,S1Start1 doNodeLifecycle init:false" msg.3="connect:540ec11c-74a7-4895-8290-7e9a6e5383c4,a94430b4-a26c-447b-a844-dba7eec47e7e" msg.4="flow:a94430b4-a26c-447b-a844-dba7eec47e7e,S1StepMain doNodeLifecycle init:true" msg.5="flow:a94430b4-a26c-447b-a844-dba7eec47e7e,S1StepMain doActivityStop" msg.6="flow:540ec11c-74a7-4895-8290-7e9a6e5383c4,S1Start1 doActivityStop"/>
</de.mhus.cherry.reactive.model.engine.RuntimeNode>
</nodes>
</step>
<step nr="3">
<cases>
<de.mhus.cherry.reactive.examples.simple1.S1Pool canonical="de.mhus.cherry.reactive.examples.simple1.S1Pool" name="S1Pool" scheduled="0" state="RUNNING" uri="bpm://de.mhus.cherry.reactive.examples.simple1.S1Process:0.0.1/de.mhus.cherry.reactive.examples.simple1.S1Pool">
<parameters text1="trigger" text2=""/>
</de.mhus.cherry.reactive.examples.simple1.S1Pool>
</cases>
<nodes>
<de.mhus.cherry.reactive.examples.simple1.trigger.S1StepTrigger assigned="null" canonical="de.mhus.cherry.reactive.examples.simple1.trigger.S1StepTrigger" name="S1StepTrigger" state="WAITING" suspended="WAITING" tryCount="3" type="HUMAN">
<parameters/>
</de.mhus.cherry.reactive.examples.simple1.trigger.S1StepTrigger>
<de.mhus.cherry.reactive.examples.simple1.S1Start1 assigned="null" canonical="de.mhus.cherry.reactive.examples.simple1.S1Start1" name="S1Start1" state="CLOSED" suspended="CLOSED" tryCount="3" type="NODE">
<parameters/>
</de.mhus.cherry.reactive.examples.simple1.S1Start1>
<de.mhus.cherry.reactive.examples.simple1.S1StepMain assigned="null" canonical="de.mhus.cherry.reactive.examples.simple1.S1StepMain" name="S1StepMain" state="CLOSED" suspended="CLOSED" tryCount="3" type="NODE">
<parameters/>
</de.mhus.cherry.reactive.examples.simple1.S1StepMain>
<de.mhus.cherry.reactive.model.engine.RuntimeNode assigned="null" canonical="de.mhus.cherry.reactive.model.engine.RuntimeNode" name="runtime" state="WAITING" suspended="WAITING" tryCount="0" type="RUNTIME">
<parameters msg.0="flow:540ec11c-74a7-4895-8290-7e9a6e5383c4,S1Start1 doNodeLifecycle init:true" msg.1="flow:540ec11c-74a7-4895-8290-7e9a6e5383c4,S1Start1 doActivityStop" msg.10="flow:4c7bf989-00f2-40a2-adf9-fc68dfbb9dc7,S1StepTrigger doActivityStop" msg.11="flow:a94430b4-a26c-447b-a844-dba7eec47e7e,S1StepMain doActivityStop" msg.2="flow:540ec11c-74a7-4895-8290-7e9a6e5383c4,S1Start1 doNodeLifecycle init:false" msg.3="connect:540ec11c-74a7-4895-8290-7e9a6e5383c4,a94430b4-a26c-447b-a844-dba7eec47e7e" msg.4="flow:a94430b4-a26c-447b-a844-dba7eec47e7e,S1StepMain doNodeLifecycle init:true" msg.5="flow:a94430b4-a26c-447b-a844-dba7eec47e7e,S1StepMain doActivityStop" msg.6="flow:540ec11c-74a7-4895-8290-7e9a6e5383c4,S1Start1 doActivityStop" msg.7="flow:a94430b4-a26c-447b-a844-dba7eec47e7e,S1StepMain doNodeLifecycle init:false" msg.8="connect:a94430b4-a26c-447b-a844-dba7eec47e7e,4c7bf989-00f2-40a2-adf9-fc68dfbb9dc7" msg.9="flow:4c7bf989-00f2-40a2-adf9-fc68dfbb9dc7,S1StepTrigger doNodeLifecycle init:true"/>
</de.mhus.cherry.reactive.model.engine.RuntimeNode>
</nodes>
</step>
<step nr="4">
<cases>
<de.mhus.cherry.reactive.examples.simple1.S1Pool canonical="de.mhus.cherry.reactive.examples.simple1.S1Pool" name="S1Pool" scheduled="0" state="RUNNING" uri="bpm://de.mhus.cherry.reactive.examples.simple1.S1Process:0.0.1/de.mhus.cherry.reactive.examples.simple1.S1Pool">
<parameters text1="trigger" text2=""/>
</de.mhus.cherry.reactive.examples.simple1.S1Pool>
</cases>
<nodes>
<de.mhus.cherry.reactive.examples.simple1.trigger.S1StepTrigger assigned="null" canonical="de.mhus.cherry.reactive.examples.simple1.trigger.S1StepTrigger" name="S1StepTrigger" state="WAITING" suspended="WAITING" tryCount="3" type="HUMAN">
<parameters/>
</de.mhus.cherry.reactive.examples.simple1.trigger.S1StepTrigger>
<de.mhus.cherry.reactive.examples.simple1.S1Start1 assigned="null" canonical="de.mhus.cherry.reactive.examples.simple1.S1Start1" name="S1Start1" state="CLOSED" suspended="CLOSED" tryCount="3" type="NODE">
<parameters/>
</de.mhus.cherry.reactive.examples.simple1.S1Start1>
<de.mhus.cherry.reactive.examples.simple1.S1StepMain assigned="null" canonical="de.mhus.cherry.reactive.examples.simple1.S1StepMain" name="S1StepMain" state="CLOSED" suspended="CLOSED" tryCount="3" type="NODE">
<parameters/>
</de.mhus.cherry.reactive.examples.simple1.S1StepMain>
<de.mhus.cherry.reactive.model.engine.RuntimeNode assigned="null" canonical="de.mhus.cherry.reactive.model.engine.RuntimeNode" name="runtime" state="WAITING" suspended="WAITING" tryCount="0" type="RUNTIME">
<parameters msg.0="flow:540ec11c-74a7-4895-8290-7e9a6e5383c4,S1Start1 doNodeLifecycle init:true" msg.1="flow:540ec11c-74a7-4895-8290-7e9a6e5383c4,S1Start1 doActivityStop" msg.10="flow:4c7bf989-00f2-40a2-adf9-fc68dfbb9dc7,S1StepTrigger doActivityStop" msg.11="flow:a94430b4-a26c-447b-a844-dba7eec47e7e,S1StepMain doActivityStop" msg.2="flow:540ec11c-74a7-4895-8290-7e9a6e5383c4,S1Start1 doNodeLifecycle init:false" msg.3="connect:540ec11c-74a7-4895-8290-7e9a6e5383c4,a94430b4-a26c-447b-a844-dba7eec47e7e" msg.4="flow:a94430b4-a26c-447b-a844-dba7eec47e7e,S1StepMain doNodeLifecycle init:true" msg.5="flow:a94430b4-a26c-447b-a844-dba7eec47e7e,S1StepMain doActivityStop" msg.6="flow:540ec11c-74a7-4895-8290-7e9a6e5383c4,S1Start1 doActivityStop" msg.7="flow:a94430b4-a26c-447b-a844-dba7eec47e7e,S1StepMain doNodeLifecycle init:false" msg.8="connect:a94430b4-a26c-447b-a844-dba7eec47e7e,4c7bf989-00f2-40a2-adf9-fc68dfbb9dc7" msg.9="flow:4c7bf989-00f2-40a2-adf9-fc68dfbb9dc7,S1StepTrigger doNodeLifecycle init:true"/>
</de.mhus.cherry.reactive.model.engine.RuntimeNode>
</nodes>
</step>
<step nr="5">
<cases>
<de.mhus.cherry.reactive.examples.simple1.S1Pool canonical="de.mhus.cherry.reactive.examples.simple1.S1Pool" name="S1Pool" scheduled="0" state="RUNNING" uri="bpm://de.mhus.cherry.reactive.examples.simple1.S1Process:0.0.1/de.mhus.cherry.reactive.examples.simple1.S1Pool">
<parameters text1="trigger" text2=""/>
</de.mhus.cherry.reactive.examples.simple1.S1Pool>
</cases>
<nodes>
<de.mhus.cherry.reactive.examples.simple1.trigger.S1StepTrigger assigned="null" canonical="de.mhus.cherry.reactive.examples.simple1.trigger.S1StepTrigger" name="S1StepTrigger" state="WAITING" suspended="WAITING" tryCount="3" type="HUMAN">
<parameters/>
</de.mhus.cherry.reactive.examples.simple1.trigger.S1StepTrigger>
<de.mhus.cherry.reactive.examples.simple1.S1Start1 assigned="null" canonical="de.mhus.cherry.reactive.examples.simple1.S1Start1" name="S1Start1" state="CLOSED" suspended="CLOSED" tryCount="3" type="NODE">
<parameters/>
</de.mhus.cherry.reactive.examples.simple1.S1Start1>
<de.mhus.cherry.reactive.examples.simple1.S1StepMain assigned="null" canonical="de.mhus.cherry.reactive.examples.simple1.S1StepMain" name="S1StepMain" state="CLOSED" suspended="CLOSED" tryCount="3" type="NODE">
<parameters/>
</de.mhus.cherry.reactive.examples.simple1.S1StepMain>
<de.mhus.cherry.reactive.model.engine.RuntimeNode assigned="null" canonical="de.mhus.cherry.reactive.model.engine.RuntimeNode" name="runtime" state="WAITING" suspended="WAITING" tryCount="0" type="RUNTIME">
<parameters msg.0="flow:540ec11c-74a7-4895-8290-7e9a6e5383c4,S1Start1 doNodeLifecycle init:true" msg.1="flow:540ec11c-74a7-4895-8290-7e9a6e5383c4,S1Start1 doActivityStop" msg.10="flow:4c7bf989-00f2-40a2-adf9-fc68dfbb9dc7,S1StepTrigger doActivityStop" msg.11="flow:a94430b4-a26c-447b-a844-dba7eec47e7e,S1StepMain doActivityStop" msg.2="flow:540ec11c-74a7-4895-8290-7e9a6e5383c4,S1Start1 doNodeLifecycle init:false" msg.3="connect:540ec11c-74a7-4895-8290-7e9a6e5383c4,a94430b4-a26c-447b-a844-dba7eec47e7e" msg.4="flow:a94430b4-a26c-447b-a844-dba7eec47e7e,S1StepMain doNodeLifecycle init:true" msg.5="flow:a94430b4-a26c-447b-a844-dba7eec47e7e,S1StepMain doActivityStop" msg.6="flow:540ec11c-74a7-4895-8290-7e9a6e5383c4,S1Start1 doActivityStop" msg.7="flow:a94430b4-a26c-447b-a844-dba7eec47e7e,S1StepMain doNodeLifecycle init:false" msg.8="connect:a94430b4-a26c-447b-a844-dba7eec47e7e,4c7bf989-00f2-40a2-adf9-fc68dfbb9dc7" msg.9="flow:4c7bf989-00f2-40a2-adf9-fc68dfbb9dc7,S1StepTrigger doNodeLifecycle init:true"/>
</de.mhus.cherry.reactive.model.engine.RuntimeNode>
</nodes>
</step>
<step nr="6">
<cases>
<de.mhus.cherry.reactive.examples.simple1.S1Pool canonical="de.mhus.cherry.reactive.examples.simple1.S1Pool" name="S1Pool" scheduled="0" state="CLOSED" uri="bpm://de.mhus.cherry.reactive.examples.simple1.S1Process:0.0.1/de.mhus.cherry.reactive.examples.simple1.S1Pool">
<parameters text1="trigger" text2=""/>
</de.mhus.cherry.reactive.examples.simple1.S1Pool>
</cases>
<nodes>
<de.mhus.cherry.reactive.examples.simple1.S1Terminate2 assigned="null" canonical="de.mhus.cherry.reactive.examples.simple1.S1Terminate2" name="S1Terminate2" state="RUNNING" suspended="RUNNING" tryCount="2" type="NODE">
<parameters/>
</de.mhus.cherry.reactive.examples.simple1.S1Terminate2>
<de.mhus.cherry.reactive.examples.simple1.trigger.S1StepTrigger assigned="null" canonical="de.mhus.cherry.reactive.examples.simple1.trigger.S1StepTrigger" name="S1StepTrigger" state="CLOSED" suspended="CLOSED" tryCount="3" type="HUMAN">
<parameters/>
</de.mhus.cherry.reactive.examples.simple1.trigger.S1StepTrigger>
<de.mhus.cherry.reactive.examples.simple1.S1Start1 assigned="null" canonical="de.mhus.cherry.reactive.examples.simple1.S1Start1" name="S1Start1" state="CLOSED" suspended="CLOSED" tryCount="3" type="NODE">
<parameters/>
</de.mhus.cherry.reactive.examples.simple1.S1Start1>
<de.mhus.cherry.reactive.examples.simple1.S1StepMain assigned="null" canonical="de.mhus.cherry.reactive.examples.simple1.S1StepMain" name="S1StepMain" state="CLOSED" suspended="CLOSED" tryCount="3" type="NODE">
<parameters/>
</de.mhus.cherry.reactive.examples.simple1.S1StepMain>
<de.mhus.cherry.reactive.model.engine.RuntimeNode assigned="null" canonical="de.mhus.cherry.reactive.model.engine.RuntimeNode" name="runtime" state="WAITING" suspended="WAITING" tryCount="0" type="RUNTIME">
<parameters msg.0="flow:540ec11c-74a7-4895-8290-7e9a6e5383c4,S1Start1 doNodeLifecycle init:true" msg.1="flow:540ec11c-74a7-4895-8290-7e9a6e5383c4,S1Start1 doActivityStop" msg.10="flow:4c7bf989-00f2-40a2-adf9-fc68dfbb9dc7,S1StepTrigger doActivityStop" msg.11="flow:a94430b4-a26c-447b-a844-dba7eec47e7e,S1StepMain doActivityStop" msg.12="connect:4c7bf989-00f2-40a2-adf9-fc68dfbb9dc7,2febd9b5-62c7-4269-af29-5f3c4ca012df" msg.13="flow:2febd9b5-62c7-4269-af29-5f3c4ca012df,S1Terminate2 doNodeLifecycle init:true" msg.14="flow:2febd9b5-62c7-4269-af29-5f3c4ca012df,S1Terminate2 doActivityStop" msg.15="flow:4c7bf989-00f2-40a2-adf9-fc68dfbb9dc7,S1StepTrigger closedActivity" msg.16="flow:2febd9b5-62c7-4269-af29-5f3c4ca012df,S1Terminate2 doNodeLifecycle init:false" msg.17="flow:2febd9b5-62c7-4269-af29-5f3c4ca012df,S1Terminate2 doActivityStop" msg.2="flow:540ec11c-74a7-4895-8290-7e9a6e5383c4,S1Start1 doNodeLifecycle init:false" msg.3="connect:540ec11c-74a7-4895-8290-7e9a6e5383c4,a94430b4-a26c-447b-a844-dba7eec47e7e" msg.4="flow:a94430b4-a26c-447b-a844-dba7eec47e7e,S1StepMain doNodeLifecycle init:true" msg.5="flow:a94430b4-a26c-447b-a844-dba7eec47e7e,S1StepMain doActivityStop" msg.6="flow:540ec11c-74a7-4895-8290-7e9a6e5383c4,S1Start1 doActivityStop" msg.7="flow:a94430b4-a26c-447b-a844-dba7eec47e7e,S1StepMain doNodeLifecycle init:false" msg.8="connect:a94430b4-a26c-447b-a844-dba7eec47e7e,4c7bf989-00f2-40a2-adf9-fc68dfbb9dc7" msg.9="flow:4c7bf989-00f2-40a2-adf9-fc68dfbb9dc7,S1StepTrigger doNodeLifecycle init:true"/>
</de.mhus.cherry.reactive.model.engine.RuntimeNode>
</nodes>
</step>
</config>
